{
  "output_root": "/mnt/beegfsstudents/home/3163450/levir_project/levir_final/submission/results/figures/figures_20260715_210451",
  "png_count": 71,
  "png_files": [
    "eda/split_change_ratio.png",
    "eda/split_empty_patch_fraction.png",
    "eda/split_image_pairs.png",
    "eda/split_patch_counts.png",
    "eda/test_patch_change_ratio_histogram.png",
    "eda/train_patch_change_ratio_histogram.png",
    "eda/val_patch_change_ratio_histogram.png",
    "history/siamese_temporal_attention_unet_train_f1.png",
    "history/siamese_temporal_attention_unet_train_iou.png",
    "history/siamese_temporal_attention_unet_train_loss.png",
    "history/siamese_temporal_attention_unet_train_precision.png",
    "history/siamese_temporal_attention_unet_train_recall.png",
    "history/siamese_temporal_attention_unet_val_f1.png",
    "history/siamese_temporal_attention_unet_val_iou.png",
    "history/siamese_temporal_attention_unet_val_loss.png",
    "history/siamese_temporal_attention_unet_val_precision.png",
    "history/siamese_temporal_attention_unet_val_recall.png",
    "history/simple_cnn_train_f1.png",
    "history/simple_cnn_train_iou.png",
    "history/simple_cnn_train_loss.png",
    "history/simple_cnn_train_precision.png",
    "history/simple_cnn_train_recall.png",
    "history/simple_cnn_val_f1.png",
    "history/simple_cnn_val_iou.png",
    "history/simple_cnn_val_loss.png",
    "history/simple_cnn_val_precision.png",
    "history/simple_cnn_val_recall.png",
    "history/unet_train_f1.png",
    "history/unet_train_iou.png",
    "history/unet_train_loss.png",
    "history/unet_train_precision.png",
    "history/unet_train_recall.png",
    "history/unet_val_f1.png",
    "history/unet_val_iou.png",
    "history/unet_val_loss.png",
    "history/unet_val_precision.png",
    "history/unet_val_recall.png",
    "metrics/model_trainable_parameters.png",
    "metrics/predicted_change_ratio.png",
    "metrics/siamese_temporal_attention_unet_threshold_f1.png",
    "metrics/siamese_temporal_attention_unet_threshold_precision.png",
    "metrics/siamese_temporal_attention_unet_threshold_recall.png",
    "metrics/simple_cnn_threshold_f1.png",
    "metrics/simple_cnn_threshold_precision.png",
    "metrics/simple_cnn_threshold_recall.png",
    "metrics/test_accuracy_bar.png",
    "metrics/test_dice_bar.png",
    "metrics/test_f1_bar.png",
    "metrics/test_iou_bar.png",
    "metrics/test_precision_bar.png",
    "metrics/test_recall_bar.png",
    "metrics/unet_threshold_f1.png",
    "metrics/unet_threshold_precision.png",
    "metrics/unet_threshold_recall.png",
    "sample/ground_truth_mask.png",
    "sample/ground_truth_overlay_on_image_b.png",
    "sample/image_a.png",
    "sample/image_b.png",
    "sample/rgb_absolute_difference.png",
    "sample/siamese_temporal_attention_unet_error_map.png",
    "sample/siamese_temporal_attention_unet_predicted_mask.png",
    "sample/siamese_temporal_attention_unet_prediction_overlay_on_image_b.png",
    "sample/siamese_temporal_attention_unet_probability_heatmap.png",
    "sample/simple_cnn_error_map.png",
    "sample/simple_cnn_predicted_mask.png",
    "sample/simple_cnn_prediction_overlay_on_image_b.png",
    "sample/simple_cnn_probability_heatmap.png",
    "sample/unet_error_map.png",
    "sample/unet_predicted_mask.png",
    "sample/unet_prediction_overlay_on_image_b.png",
    "sample/unet_probability_heatmap.png"
  ],
  "eda_summary": {
    "train": {
      "images": 445,
      "patches": 7120,
      "changed_pixels": 21412971,
      "total_pixels": 466616320,
      "change_ratio": 0.045889888720565965,
      "empty_patch_fraction": 0.5551966292134831,
      "patch_change_ratio_mean": 0.045889888720565965,
      "patch_change_ratio_median": 0.0
    },
    "val": {
      "images": 64,
      "patches": 1024,
      "changed_pixels": 2816268,
      "total_pixels": 67108864,
      "change_ratio": 0.04196566343307495,
      "empty_patch_fraction": 0.57421875,
      "patch_change_ratio_mean": 0.04196566343307495,
      "patch_change_ratio_median": 0.0
    },
    "test": {
      "images": 128,
      "patches": 2048,
      "changed_pixels": 6837404,
      "total_pixels": 134217728,
      "change_ratio": 0.05094262957572937,
      "empty_patch_fraction": 0.54345703125,
      "patch_change_ratio_mean": 0.05094262957572937,
      "patch_change_ratio_median": 0.0
    }
  },
  "sample": {
    "metadata": {
      "source_image": "test_34.png",
      "patch_top": 768,
      "patch_left": 0,
      "patch_size": 256,
      "sample_name": "test_34_y768_x0",
      "dataset_index": 908,
      "change_ratio": 0.0552978515625,
      "threshold": 0.5
    },
    "sample_metrics": [
      {
        "model": "simple_cnn",
        "threshold": 0.5,
        "precision": 0.592689295028111,
        "recall": 0.8769315673047204,
        "f1": 0.7073224535239334,
        "iou": 0.5471763085305238,
        "dice": 0.7073225016613919,
        "accuracy": 0.9598693847641604,
        "pred_change_ratio": 0.08181762695300016,
        "true_change_ratio": 0.05529785156241562
      },
      {
        "model": "unet",
        "threshold": 0.5,
        "precision": 0.8868279569654078,
        "recall": 0.9103200882751016,
        "f1": 0.8984204292869118,
        "iou": 0.8155747836633974,
        "dice": 0.8984204792905989,
        "accuracy": 0.9886169433578664,
        "pred_change_ratio": 0.05676269531241339,
        "true_change_ratio": 0.05529785156241562
      },
      {
        "model": "siamese_temporal_attention_unet",
        "threshold": 0.5,
        "precision": 0.9411605205818557,
        "recall": 0.9577814569272136,
        "f1": 0.9493981994308189,
        "iou": 0.9036709190079752,
        "dice": 0.94939824943997,
        "accuracy": 0.9943542480453578,
        "pred_change_ratio": 0.05627441406241413,
        "true_change_ratio": 0.05529785156241562
      }
    ]
  }
}